{"http://ontology.ogham.link/context": ["{string}"], "http://ontology.ogham.link/exactMatch": ["http://www.wikidata.org/entity/Q106703740"], "http://ontology.ogham.link/reference": ["McManus 1991,\u00a76.9"], "http://ontology.ogham.link/translation": ["winter + wolf"], "http://purl.org/dc/terms/creator": ["https://orcid.org/0000-0002-3246-3531"], "http://purl.org/dc/terms/license": ["https://creativecommons.org/licenses/by/4.0/deed.de"], "http://purl.org/dc/terms/rightsHolder": ["https://orcid.org/0000-0002-3246-3531", "http://www.wikidata.org/entity/Q70310399"], "http://www.w3.org/1999/02/22-rdf-syntax-ns#type": ["http://ontology.ogham.link/Word", "http://www.w3.org/2004/02/skos/core#Concept"], "http://www.w3.org/2000/01/rdf-schema#label": ["GAMICUNAS", "GAMICUNAS"], "http://www.w3.org/2004/02/skos/core#altLabel": ["GAMICUNAS", "GAMICUNAS"], "http://www.w3.org/2004/02/skos/core#prefLabel": ["GAMICUNAS", "GAMICUNAS"], "http://www.w3.org/ns/prov#wasAttributedTo": ["http://lod.ogham.link/data/PythonStonesCIIC"], "http://www.w3.org/ns/prov#wasDerivedFrom": ["https://github.com/ogi-ogham/ogham-datav1/blob/main/csv/ogham/og_words.csv"], "http://www.w3.org/ns/prov#wasGeneratedBy": ["http://lod.ogham.link/data/OW90_activity"]}